{
  "schemaVersion": 1,
  "id": "syringe",
  "version": "${version}",
  "name": "Syringe",
  "description": "// TODO",
  "icon": "assets/syringe/icon.png",
  "license": "Apache-2.0",
  "environment": "client",
  "accessWidener": "syringe.accesswidener",
  "contact": {
    "sources": "https://github.com/uTen2c/syringe",
    "issues": "https://github.com/uTen2c/syringe/issues"
  },
  "entrypoints": {
    "main": [
      "dev.uten2c.syringe.SyringeMod"
    ]
  },
  "mixins": [
    "syringe.mixins.json"
  ],
  "depends": {
    "minecraft": ">=1.18",
    "fabricloader": ">=0.11.6"
  }
}
